{"photos":[
	{"pid":1, "uid":1,	"path":"/shared/1.png",	"timestamp":1392405505782},
	{"pid":2, "uid":1,	"path":"/shared/2.png",	"timestamp":1392405505782},
	{"pid":3, "uid":1,	"path":"/shared/3.png",	"timestamp":1392405505782},
	{"pid":4, "uid":1,	"path":"/shared/4.png",	"timestamp":1392405505782},
	{"pid":5, "uid":1,	"path":"/shared/5.png",	"timestamp":1392405505782},
	{"pid":6, "uid":1,	"path":"/shared/6.png",	"timestamp":1392405505782},
	{"pid":7, "uid":1,	"path":"/shared/7.png",	"timestamp":1392405505782},
	{"pid":8, "uid":1,	"path":"/shared/8.png",	"timestamp":1392405505782},
	{"pid":9, "uid":1,	"path":"/shared/9.png",	 "timestamp":1392405505782},
	{"pid":10,"uid":1,	"path":"/shared/10.png",    "timestamp":1392405505782},
	{"pid":11,"uid":1,	"path":"/shared/11.png",	"timestamp":1392405505782},
	{"pid":12,"uid":1,	"path":"/shared/12.png",	"timestamp":1392405505782},
	{"pid":13,"uid":1,	"path":"/shared/13.png",	"timestamp":1392405505782},
	{"pid":14,"uid":1,	"path":"/shared/14.png",	"timestamp":1392405505782},
	{"pid":15,"uid":1,	"path":"/shared/15.png",	"timestamp":1392405505782},
	{"pid":16,"uid":1,	"path":"/shared/16.png",	"timestamp":1392405505782},
	{"pid":17,"uid":1,	"path":"/shared/17.png",	"timestamp":1392405505782},
	{"pid":18,"uid":1,	"path":"/shared/18.png",	"timestamp":1392405505782},
	{"pid":19,"uid":1,	"path":"/shared/19.png",	"timestamp":1392405505782},
	{"pid":20,"uid":1,	"path":"/shared/20.png",	"timestamp":1392405505782},
	{"pid":21,"uid":1,	"path":"/shared/21.png",	"timestamp":1392405505782},
	{"pid":22,"uid":1,	"path":"/shared/22.png",	"timestamp":1392405505782},
	{"pid":23,"uid":1,	"path":"/shared/23.png",	"timestamp":1392405505782},
	{"pid":24,"uid":1,	"path":"/shared/24.png",	"timestamp":1392405505782},
	{"pid":25,"uid":1,	"path":"/shared/25.png",	"timestamp":1392405505782},
	{"pid":26,"uid":1,	"path":"/shared/26.png",	"timestamp":1392405505782},
	{"pid":27,"uid":1,	"path":"/shared/27.png",	"timestamp":1392405505782},
	{"pid":28,"uid":1,	"path":"/shared/28.png",	"timestamp":1392405505782},
	{"pid":29,"uid":1,	"path":"/shared/29.png",	"timestamp":1392405505782},
	{"pid":30,"uid":1,	"path":"/shared/30.png",	"timestamp":1392405505782}
]}